CHANGES.txt
MANIFEST.in
setup.py
src/gocept/__init__.py
src/gocept.linkchecker.egg-info/PKG-INFO
src/gocept.linkchecker.egg-info/SOURCES.txt
src/gocept.linkchecker.egg-info/dependency_links.txt
src/gocept.linkchecker.egg-info/namespace_packages.txt
src/gocept.linkchecker.egg-info/not-zip-safe
src/gocept.linkchecker.egg-info/requires.txt
src/gocept.linkchecker.egg-info/top_level.txt
src/gocept/linkchecker/LinkCheckerTool.py
src/gocept/linkchecker/README.txt
src/gocept/linkchecker/__init__.py
src/gocept/linkchecker/configure.zcml
src/gocept/linkchecker/database.py
src/gocept/linkchecker/exceptions.py
src/gocept/linkchecker/interfaces.py
src/gocept/linkchecker/lchtmllib.py
src/gocept/linkchecker/link.py
src/gocept/linkchecker/log.py
src/gocept/linkchecker/permissions.py
src/gocept/linkchecker/reports.py
src/gocept/linkchecker/retrievemanager.py
src/gocept/linkchecker/retrievers.py
src/gocept/linkchecker/shorturls.py
src/gocept/linkchecker/tool.gif
src/gocept/linkchecker/tool.png
src/gocept/linkchecker/url.py
src/gocept/linkchecker/utils.py
src/gocept/linkchecker/version.txt
src/gocept/linkchecker/Extensions/Install.py
src/gocept/linkchecker/doc/AUTHORS.txt
src/gocept/linkchecker/doc/DEPENDENCIES.txt
src/gocept/linkchecker/doc/HOWTO-Developers.txt
src/gocept/linkchecker/doc/README.txt
src/gocept/linkchecker/doc/STATES.txt
src/gocept/linkchecker/doc/Scheduling.txt
src/gocept/linkchecker/doc/TODO.txt
src/gocept/linkchecker/doc/features/BrokenLinksPortlet.png
src/gocept/linkchecker/doc/features/ColouredLinks.png
src/gocept/linkchecker/doc/features/FEATURES.txt
src/gocept/linkchecker/doc/features/ManagementOverview.png
src/gocept/linkchecker/doc/features/MyLinks.png
src/gocept/linkchecker/doc/features/ObjectOverview.png
src/gocept/linkchecker/doc/features/ReferencedBy.png
src/gocept/linkchecker/doc/features/ReferencedByFolderListing.png
src/gocept/linkchecker/doc/features/ReferencedByPortlet.png
src/gocept/linkchecker/locales/de/LC_MESSAGES/gocept.linkchecker.po
src/gocept/linkchecker/profiles/default/actionicons.xml
src/gocept/linkchecker/profiles/default/actions.xml
src/gocept/linkchecker/profiles/default/controlpanel.xml
src/gocept/linkchecker/profiles/default/metadata.xml
src/gocept/linkchecker/profiles/default/portlets.xml
src/gocept/linkchecker/profiles/default/skins.xml
