Metadata-Version: 1.0
Name: gocept.linkchecker
Version: 3.0a6
Summary: Check links in your Plone site using a link monitoring server.
Home-page: UNKNOWN
Author: gocept gmbh & co. kg
Author-email: mail@gocept.com
License: ZPL 2.1
Platform: UNKNOWN
